hdl21schematicimporter/__init__.py
hdl21schematicimporter/circuit.py
hdl21schematicimporter/code.py
hdl21schematicimporter/pyimporter.py
hdl21schematicimporter/svg.py
hdl21schematicimporter/svgdefs.py
hdl21schematicimporter-1.0.dev0.dist-info/LICENSE
hdl21schematicimporter-1.0.dev0.dist-info/WHEEL
hdl21schematicimporter-1.0.dev0.dist-info/METADATA
hdl21schematicimporter-1.0.dev0.dist-info/RECORD
